be_great_v/__init__.py
be_great_v/great.py
be_great_v/great_dataset.py
be_great_v/great_start.py
be_great_v/great_trainer.py
be_great_v/great_utils.py
be_great_v-0.1.3.dist-info/LICENSE
be_great_v-0.1.3.dist-info/METADATA
be_great_v-0.1.3.dist-info/WHEEL
be_great_v-0.1.3.dist-info/top_level.txt
be_great_v-0.1.3.dist-info/RECORD
