Metadata-Version: 2.1
Name: be-great-v
Version: 0.1.3
Summary: (A Fork)Generating Realistic Tabular Data using Large Language Models
Author-email: Tim Saijun <code@zair.top>, Kathrin Sessler <kathrin.sessler@tum.de>, Vadim Borisov <vadim.borisov@uni-tuebingen.de>
License: MIT License
Project-URL: Homepage, https://github.com/Tim-Saijun/be_great
Project-URL: Documentation, https://kathrinse.github.io/be_great/
Keywords: great,pytorch,tabular data,data generation,transformer,language models,deep learning
Classifier: Programming Language :: Python :: 3
Classifier: License :: OSI Approved :: MIT License
Classifier: Operating System :: OS Independent
Requires-Python: >=3.9
License-File: LICENSE
Requires-Dist: datasets >=2.5.2
Requires-Dist: numpy >=1.23.1
Requires-Dist: pandas >=1.4.4
Requires-Dist: scikit-learn >=1.1.1
Requires-Dist: torch >=1.10.2
Requires-Dist: tqdm >=4.64.1
Requires-Dist: transformers >=4.22.1
Requires-Dist: accelerate >=0.20.1
Requires-Dist: peft
